zhipuai_ml/__init__.py
zhipuai_ml/main.py
zhipuai_ml-0.1.1.dist-info/METADATA
zhipuai_ml-0.1.1.dist-info/WHEEL
zhipuai_ml-0.1.1.dist-info/top_level.txt
zhipuai_ml-0.1.1.dist-info/RECORD
