Metadata-Version: 2.1
Name: zhipuai_ml
Version: 0.1.1
Summary: A package with machine learning tasks
Author: kkl
Author-email: kkl2@gmail.com
Classifier: Programming Language :: Python :: 3
Classifier: License :: OSI Approved :: MIT License
Classifier: Operating System :: OS Independent
Requires-Python: >=3.6
